firstmail/__init__.py
firstmail/__main__.py
firstmail/base.py
firstmail/cli.py
tests/__init__.py
tests/core_test.py
firstmail-0.1.2.dist-info/METADATA
firstmail-0.1.2.dist-info/WHEEL
firstmail-0.1.2.dist-info/entry_points.txt
firstmail-0.1.2.dist-info/top_level.txt
firstmail-0.1.2.dist-info/RECORD
