Metadata-Version: 2.4
Name: firstmail
Version: 0.1.2
Summary: Integrate firstmail.ltd emails into your Python applications with ease.
Author-email: nichind <nichind@proton.me>
License: MIT
Project-URL: Homepage, https://github.com/nichind/firstmail
Project-URL: Issues, https://github.com/nichind/firstmail/issues
Keywords: firstmail
Classifier: Programming Language :: Python :: 3.9
Classifier: License :: OSI Approved :: MIT License
Classifier: Operating System :: OS Independent
Requires-Python: >=3.9
Requires-Dist: psutil
Requires-Dist: pysocks
